osdental_mobile_library/__init__.py
osdental_mobile_library/Database/Connection.py
osdental_mobile_library/Database/__init__.py
osdental_mobile_library/Decorators/AuditLogMobile.py
osdental_mobile_library/Decorators/__init__.py
osdental_mobile_library/Exception/ControlledException.py
osdental_mobile_library/Exception/__init__.py
osdental_mobile_library/InternalHttp/__init__.py
osdental_mobile_library/Models/Catalog.py
osdental_mobile_library/Models/Response.py
osdental_mobile_library/Models/__init__.py
osdental_mobile_library/ServicesBus/ServicesBus.py
osdental_mobile_library/ServicesBus/TaskQueue.py
osdental_mobile_library/ServicesBus/__init__.py
osdental_mobile_library/Shared/Logger.py
osdental_mobile_library/Shared/__init__.py
osdental_mobile_library/Shared/Enums/Code.py
osdental_mobile_library/Shared/Enums/Constant.py
osdental_mobile_library/Shared/Enums/FileType.py
osdental_mobile_library/Shared/Enums/Message.py
osdental_mobile_library/Shared/Enums/Profile.py
osdental_mobile_library/Shared/Enums/__init__.py
osdental_mobile_library/Shared/Utils/CaseConverter.py
osdental_mobile_library/Shared/Utils/CodeGenerator.py
osdental_mobile_library/Shared/Utils/DataUtils.py
osdental_mobile_library/Shared/Utils/DateUtils.py
osdental_mobile_library/Shared/Utils/FileMetaData.py
osdental_mobile_library/Shared/Utils/Mapper.py
osdental_mobile_library/Shared/Utils/PasswordGenerator.py
osdental_mobile_library/Shared/Utils/TextProcessor.py
osdental_mobile_library/Shared/Utils/__init__.py
osdental_mobile_library-0.1.4.dist-info/METADATA
osdental_mobile_library-0.1.4.dist-info/WHEEL
osdental_mobile_library-0.1.4.dist-info/top_level.txt
osdental_mobile_library-0.1.4.dist-info/RECORD
